stactools/esa_cci_lc/__init__.py
stactools/esa_cci_lc/classes.py
stactools/esa_cci_lc/cog.py
stactools/esa_cci_lc/commands.py
stactools/esa_cci_lc/constants.py
stactools/esa_cci_lc/netcdf.py
stactools/esa_cci_lc/stac.py
stactools_esa_cci_lc-0.1.0.dist-info/LICENSE
stactools_esa_cci_lc-0.1.0.dist-info/METADATA
stactools_esa_cci_lc-0.1.0.dist-info/WHEEL
stactools_esa_cci_lc-0.1.0.dist-info/top_level.txt
stactools_esa_cci_lc-0.1.0.dist-info/RECORD
