Metadata-Version: 2.1
Name: stactools-esa-cci-lc
Version: 0.1.0
Summary: stactools package for ESA''s Climate Change Initiative (CCI) Land Cover (LC) product
Home-page: https://github.com/stactools-packages/esa-cci-lc
Author: Matthias Mohr
Author-email: matthias.mohr@radiant.earth
Project-URL: Issues, https://github.com/stactools-packages/esa-cci-lc/issues
Keywords: stactools,esa,cci,land cover,climate change,STAC
Classifier: Development Status :: 4 - Beta
Classifier: License :: OSI Approved :: Apache Software License
Classifier: Programming Language :: Python :: 3.8
Classifier: Programming Language :: Python :: 3.9
Classifier: Programming Language :: Python :: 3.10
License-File: LICENSE
Requires-Dist: stactools (>=0.4.0)
Requires-Dist: python-dateutil (>=2.7.0)
Requires-Dist: types-python-dateutil (>=2.7.0)
Requires-Dist: netCDF4 (>=1.6.0)
Requires-Dist: pystac (>=1.6.1)
Requires-Dist: rasterio (>=1.3.0)
Requires-Dist: rioxarray (>=0.12.1)
Requires-Dist: GDAL (>=3.4.0)
